{
	"configurations" : 
	[
		{
			"directories" : 
			[
				{
					"build" : ".",
					"jsonFile" : "directory-.-Debug-d0094a50bb2071803777.json",
					"minimumCMakeVersion" : 
					{
						"string" : "3.28"
					},
					"projectIndex" : 0,
					"source" : ".",
					"targetIndexes" : 
					[
						0
					]
				}
			],
			"name" : "Debug",
			"projects" : 
			[
				{
					"directoryIndexes" : 
					[
						0
					],
					"name" : "module06",
					"targetIndexes" : 
					[
						0
					]
				}
			],
			"targets" : 
			[
				{
					"directoryIndex" : 0,
					"id" : "exercise01::@6890427a1f51a3e7e1df",
					"jsonFile" : "target-exercise01-Debug-c6c29cf9950e31e15a95.json",
					"name" : "exercise01",
					"projectIndex" : 0
				}
			]
		}
	],
	"kind" : "codemodel",
	"paths" : 
	{
		"build" : "C:/var/workspace/github/dcl115-2024-aug-12/module06/cmake-build-debug",
		"source" : "C:/var/workspace/github/dcl115-2024-aug-12/module06"
	},
	"version" : 
	{
		"major" : 2,
		"minor" : 6
	}
}
